projeth19/__init__.py
projeth19-0.0.3.dist-info/METADATA
projeth19-0.0.3.dist-info/RECORD
projeth19-0.0.3.dist-info/WHEEL
projeth19-0.0.3.dist-info/top_level.txt
