Metadata-Version: 2.1
Name: projeth19
Version: 0.0.3
Summary: Projet GCB202 H19
Home-page: https://catalyseur.ca
Author: Francis B. Lavoie
Author-email: francis.b.lavoie@usherbrooke.ca
License: UNKNOWN
Platform: UNKNOWN
Classifier: Programming Language :: Python :: 3
Classifier: License :: OSI Approved :: MIT License
Classifier: Operating System :: OS Independent
